hnt_sap_nf/__init__.py
hnt_sap_nf/hnt_sap_exception.py
hnt_sap_nf/hnt_sap_gui.py
hnt_sap_nf/j1b1n_transaction.py
hnt_sap_nf/common/sap_status_bar.py
hnt_sap_nf/common/session.py
hnt_sap_nf/common/tx_result.py
hnt_sap_nf_caixas-0.0.3.dist-info/METADATA
hnt_sap_nf_caixas-0.0.3.dist-info/WHEEL
hnt_sap_nf_caixas-0.0.3.dist-info/top_level.txt
hnt_sap_nf_caixas-0.0.3.dist-info/RECORD
