Metadata-Version: 2.4
Name: hnt_sap_nf_caixas
Version: 0.0.3
Summary: Lib to access sap gui to run transactions
Author: Pepe
License: MIT License
Keywords: nota_fiscal
Requires-Dist: python-dotenv
Requires-Dist: robotframework-sapguilibrary
Dynamic: author
Dynamic: keywords
Dynamic: license
Dynamic: requires-dist
Dynamic: summary
